amgi_sqs_event_source_mapping/__init__.py
amgi_sqs_event_source_mapping/py.typed
amgi_sqs_event_source_mapping-0.32.0.dist-info/licenses/LICENSE
amgi_sqs_event_source_mapping-0.32.0.dist-info/WHEEL
amgi_sqs_event_source_mapping-0.32.0.dist-info/METADATA
amgi_sqs_event_source_mapping-0.32.0.dist-info/RECORD
