Metadata-Version: 2.4
Name: amgi-sqs-event-source-mapping
Version: 0.32.0
Summary: AMGI SQS event source mapping handler
Author: jack.burridge
Author-email: jack.burridge <jack.burridge@mail.com>
License-Expression: MIT
License-File: LICENSE
Classifier: Programming Language :: Python :: 3 :: Only
Classifier: Programming Language :: Python :: 3.10
Classifier: Programming Language :: Python :: 3.11
Classifier: Programming Language :: Python :: 3.12
Classifier: Programming Language :: Python :: 3.13
Classifier: Programming Language :: Python :: 3.14
Requires-Dist: amgi-common==0.32.0
Requires-Dist: amgi-types==0.32.0
Requires-Dist: typing-extensions>=4.15.0 ; python_full_version < '3.11'
Requires-Dist: boto3>=1.40.70 ; extra == 'boto3'
Requires-Python: >=3.10
Provides-Extra: boto3
